flspp/__init__.py
flspp/_core.cpp
flspp/core.py
flspp/cpp/additional_vector_stuff.h
flspp/cpp/clustering.cpp
flspp/cpp/clustering.h
flspp/cpp/clustering_algorithm.cpp
flspp/cpp/clustering_algorithm.h
flspp/cpp/makros.cpp
flspp/cpp/makros.h
flspp/cpp/random_generator.cpp
flspp/cpp/random_generator.h
flspp/_core.cpython-310-x86_64-linux-gnu.so
flspp-0.1.6.dist-info/LICENSE
flspp-0.1.6.dist-info/METADATA
flspp-0.1.6.dist-info/WHEEL
flspp-0.1.6.dist-info/RECORD
