Metadata-Version: 2.1
Name: flspp
Version: 0.1.6
Summary: Implementation of the FLS++ algorithm for K-Means clustering.
License: LICENSE
Author: Lukas Drexler
Author-email: lukas.drexler@hhu.de
Requires-Python: >=3.9,<4.0
Classifier: License :: Other/Proprietary License
Classifier: Programming Language :: Python :: 3
Classifier: Programming Language :: Python :: 3.9
Classifier: Programming Language :: Python :: 3.10
Classifier: Programming Language :: Python :: 3.11
Classifier: Programming Language :: Python :: 3.12
Requires-Dist: numpy (>=1.26.4,<2.0.0)
Requires-Dist: scikit-learn (>=1.4.2,<2.0.0)
